Metadata-Version: 1.1
Name: opbeat-python-urllib3
Version: 1.1
Summary: An urllib3 transport for Opbeat
Home-page: https://github.com/opbeat/opbeat_python_urllib3
Author: Opbeat, Inc
Author-email: support@opbeat.com
License: UNKNOWN
Platform: UNKNOWN
Classifier: Intended Audience :: Developers
Classifier: Intended Audience :: System Administrators
Classifier: Operating System :: OS Independent
Classifier: Topic :: Software Development
Classifier: Programming Language :: Python
Classifier: Programming Language :: Python :: 2.6
Classifier: Programming Language :: Python :: 2.7
Classifier: Programming Language :: Python :: 3.3
Classifier: Programming Language :: Python :: 3.4
